{"audience_analysis": "## Audience Analysis\n\n### Profile:\n- **Course Topic:** Python programing\n- **Audience Type:** beginner\n- **Common Job Titles/Background:** Learners interested in Python programing.\n\n### Key Characteristics:\n- **Knowledge Base:** Limited exposure to the subject matter, with basic foundational knowledge.\n- **Learning Style:** Various learning preferences requiring a mix of theoretical and practical approaches.\n- **Motivation:** Interest in acquiring or improving skills related to Python programing.\n- **Needs:** Structured learning path with appropriate examples and practice opportunities.\n\n### Implications for Instructional Design:\n- Provide clear explanations with relevant examples appropriate for beginner level.\n- Include a mix of theoretical concepts and practical applications.\n- Create opportunities for hands-on practice to reinforce learning.\n", "course_topic": "Python programing", "audience_type": "beginner", "job_titles": "12th standard student", "generated_date": "April 11, 2025 at 12:17"}